babblebox/__init__.py
babblebox_pkg/__init__.py
chatbot_package/__init__.py
babblebox-0.2.1.dist-info/LICENSE
babblebox-0.2.1.dist-info/METADATA
babblebox-0.2.1.dist-info/WHEEL
babblebox-0.2.1.dist-info/top_level.txt
babblebox-0.2.1.dist-info/RECORD
